{
  "main": {
    "id": "acca760ecf3db4bf",
    "type": "split",
    "children": [
      {
        "id": "d1e642f9403a8334",
        "type": "tabs",
        "children": [
          {
            "id": "17356f40fe7cc05f",
            "type": "leaf",
            "state": {
              "type": "image",
              "state": {
                "file": "img/Pasted image 20240421173259.png"
              }
            }
          }
        ]
      }
    ],
    "direction": "vertical"
  },
  "left": {
    "id": "37f111b5e3d6c951",
    "type": "split",
    "children": [
      {
        "id": "4c3ce2e0abd46323",
        "type": "tabs",
        "children": [
          {
            "id": "11a40ab14882c66c",
            "type": "leaf",
            "state": {
              "type": "file-explorer",
              "state": {
                "sortOrder": "alphabetical"
              }
            }
          },
          {
            "id": "de6e4916d7168889",
            "type": "leaf",
            "state": {
              "type": "search",
              "state": {
                "query": "",
                "matchingCase": false,
                "explainSearch": false,
                "collapseAll": false,
                "extraContext": false,
                "sortOrder": "alphabetical"
              }
            }
          },
          {
            "id": "9c20c451fecd08eb",
            "type": "leaf",
            "state": {
              "type": "bookmarks",
              "state": {}
            }
          }
        ]
      }
    ],
    "direction": "horizontal",
    "width": 387.5
  },
  "right": {
    "id": "5e696f9cfa3a3c16",
    "type": "split",
    "children": [
      {
        "id": "16735f33daaaa666",
        "type": "tabs",
        "children": [
          {
            "id": "540c039e1df61654",
            "type": "leaf",
            "state": {
              "type": "backlink",
              "state": {
                "file": "img/Pasted image 20240421173259.png",
                "collapseAll": false,
                "extraContext": false,
                "sortOrder": "alphabetical",
                "showSearch": false,
                "searchQuery": "",
                "backlinkCollapsed": false,
                "unlinkedCollapsed": true
              }
            }
          },
          {
            "id": "0a93a84c9fd6952c",
            "type": "leaf",
            "state": {
              "type": "outgoing-link",
              "state": {
                "file": "img/Pasted image 20240421173259.png",
                "linksCollapsed": false,
                "unlinkedCollapsed": true
              }
            }
          },
          {
            "id": "b798f3dc5bd815e5",
            "type": "leaf",
            "state": {
              "type": "tag",
              "state": {
                "sortOrder": "frequency",
                "useHierarchy": true
              }
            }
          },
          {
            "id": "09bd50d2dbf33988",
            "type": "leaf",
            "state": {
              "type": "outline",
              "state": {
                "file": "img/Pasted image 20240421173259.png"
              }
            }
          }
        ]
      }
    ],
    "direction": "horizontal",
    "width": 300,
    "collapsed": true
  },
  "left-ribbon": {
    "hiddenItems": {
      "switcher:Open quick switcher": false,
      "graph:Open graph view": false,
      "canvas:Create new canvas": false,
      "daily-notes:Open today's daily note": false,
      "templates:Insert template": false,
      "command-palette:Open command palette": false
    }
  },
  "active": "11a40ab14882c66c",
  "lastOpenFiles": [
    "notes/23- DynamoDB/23.04- DynamoDB Features.md",
    "img/Pasted image 20240421202753.png",
    "notes/23- DynamoDB/23.05- DynamoDB Global Tables.md",
    "notes/23- DynamoDB/23.04- DynamoDB Streams.md",
    "img/Pasted image 20240421201630.png",
    "notes/23- DynamoDB/23.03- DynamoDB Accelerator (DAX).md",
    "img/Pasted image 20240421200745.png",
    "notes/23- DynamoDB/23.02- DynamoDB Capacity Modes.md",
    "notes/23- DynamoDB/23.01- DynamoDB (Serverless DB).md",
    "notes/22- Lambda/22.08- Lambda + RDS.md",
    "notes/23- DynamoDB",
    "notes/18- SNS/18.05- FIFO Topics.md",
    "notes/18- SNS/18.04- SNS+S3 Event Rule.md",
    "notes/17- SQS/17.05- SQS+ASG.md",
    "notes/10- S3/10.09- S3 Event Notification.md",
    "img/Pasted image 20240421194645.png",
    "notes/22- Lambda/22.07- Lambda + VPC.md",
    "img/Pasted image 20240421175034.png",
    "img/Pasted image 20240421174502.png",
    "img/Pasted image 20240421174249.png",
    "notes/22- Lambda/22.06- Lambda + Edge Servers.md",
    "img/Pasted image 20240421173317.png",
    "img/Pasted image 20240421173259.png",
    "notes/22- Lambda/22.05- Lambda SnapStart.md",
    "notes/22- Lambda/22.04- Lambda Limits.md",
    "notes/22- Lambda/22.03- Lambda Pricing.md",
    "img/Pasted image 20240421170000.png",
    "notes/22- Lambda/22.02- Lambda Use Cases.md",
    "notes/22- Lambda/22.01- AWS Lambda.md",
    "notes/21- ECS/21.06- Some ECS Architecture.md",
    "notes/22- Lambda",
    "notes/19- Kinesis/19.07- Kinesis vs SQS FIFO.md",
    "notes/19- Kinesis/19.04- KDS Security.md",
    "notes/21- ECS/21.05- ECS Auto Scaling Group.md",
    "notes/21- ECS/21.04- ECS + EFS.md",
    "notes/21- ECS/21.03- ECS + Load Balancers.md",
    "notes/21- ECS/21.02- ECS IAMs.md",
    "notes/21- ECS",
    "notes/20- AWS MQ",
    "notes/19- Kinesis/Untitled",
    "notes/19- Kinesis",
    "notes/18- SNS/Untitled",
    "notes/18- SNS",
    "notes/17- SQS",
    "notes/16- AWS DataSync",
    "Untitled.canvas"
  ]
}